LICENSE.txt
MANIFEST.in
README.rst
setup.cfg
setup.py
django_environ_docker.egg-info/PKG-INFO
django_environ_docker.egg-info/SOURCES.txt
django_environ_docker.egg-info/dependency_links.txt
django_environ_docker.egg-info/not-zip-safe
django_environ_docker.egg-info/requires.txt
django_environ_docker.egg-info/top_level.txt
environ/__init__.py
environ/environ.py
environ/test.py
environ/test_env.txt