Metadata-Version: 1.1
Name: django-environ-docker
Version: 0.5.0
Summary: Django-environ-docker allows you to utilize 12factor inspired environment variables to configure your Django application with Docker Secrets.
Home-page: https://github.com/netquity/django-environ
Author: Netquity
Author-email: hello@netquity.com
License: MIT License
Download-URL: https://github.com/netquity/django-environ/archive/0.5.0.tar.gz
Keywords: d,j,a,n,g,o, ,e,n,v,i,r,o,n,m,e,n,t, ,v,a,r,i,a,b,l,e,s, ,1,2,f,a,c,t,o,r, ,d,o,c,k,e,r, ,s,e,c,r,e,t,s
Platform: any
Classifier: Development Status :: 3 - Alpha
Classifier: Intended Audience :: Information Technology
Classifier: Framework :: Django
Classifier: Framework :: Django :: 1.8
Classifier: Framework :: Django :: 1.9
Classifier: Framework :: Django :: 1.10
Classifier: Framework :: Django :: 1.11
Classifier: Programming Language :: Python
Classifier: Programming Language :: Python :: 2
Classifier: Programming Language :: Python :: 2.7
Classifier: Programming Language :: Python :: 3
Classifier: Programming Language :: Python :: 3.4
Classifier: Programming Language :: Python :: 3.5
Classifier: Programming Language :: Python :: Implementation :: CPython
Classifier: Programming Language :: Python :: Implementation :: PyPy
Classifier: Topic :: Software Development :: Libraries :: Python Modules
Classifier: Topic :: Utilities
Classifier: License :: OSI Approved :: MIT License
Classifier: Framework :: Django
